all_clip/__init__.py
all_clip/deepsparse_clip.py
all_clip/hf_clip.py
all_clip/ja_clip.py
all_clip/main.py
all_clip/open_clip.py
all_clip/openai_clip.py
all_clip-1.3.0.data/data/README.md
all_clip-1.3.0.dist-info/LICENSE
all_clip-1.3.0.dist-info/METADATA
all_clip-1.3.0.dist-info/WHEEL
all_clip-1.3.0.dist-info/top_level.txt
all_clip-1.3.0.dist-info/RECORD
