Metadata-Version: 2.1
Name: all-clip
Version: 1.3.0
Summary: Load any clip model with a standardized interface
Home-page: https://github.com/data2ml/all_clip
Author: Romain Beaumont
Author-email: romain.rom1@gmail.com
License: MIT
Keywords: machine learning
Classifier: Development Status :: 4 - Beta
Classifier: Intended Audience :: Developers
Classifier: Topic :: Scientific/Engineering :: Artificial Intelligence
Classifier: License :: OSI Approved :: MIT License
Classifier: Programming Language :: Python :: 3.8
License-File: LICENSE
Requires-Dist: torch
Requires-Dist: clip-anytorch<3,>=2.5.0
Requires-Dist: open-clip-torch<3.0.0,>=2.0.0
Requires-Dist: multilingual-clip<2,>=1.0.10
Requires-Dist: transformers
Requires-Dist: numpy
